tf2_utils/__init__.py
tf2_utils/currency.py
tf2_utils/exceptions.py
tf2_utils/inventory.py
tf2_utils/item.py
tf2_utils/item_name.py
tf2_utils/marketplace_tf.py
tf2_utils/offer.py
tf2_utils/prices_tf.py
tf2_utils/prices_tf_websocket.py
tf2_utils/schema.py
tf2_utils/sku.py
tf2_utils/utils.py
tf2_utils/providers/custom.py
tf2_utils/providers/express_load.py
tf2_utils/providers/provider.py
tf2_utils/providers/providers.py
tf2_utils/providers/steam_supply.py
tf2_utils/providers/steamapis.py
tf2_utils/providers/steamcommunity.py
tf2_utils-2.3.5.dist-info/licenses/LICENSE
tf2_utils-2.3.5.dist-info/METADATA
tf2_utils-2.3.5.dist-info/WHEEL
tf2_utils-2.3.5.dist-info/top_level.txt
tf2_utils-2.3.5.dist-info/RECORD
