Metadata-Version: 2.4
Name: tf2-utils
Version: 2.3.5
Summary: Tools and utilities for TF2 trading
Author-email: offish <overutilization@gmail.com>
Project-URL: Homepage, https://github.com/offish/tf2-utils
Project-URL: Bug Tracker, https://github.com/offish/tf2-utils/issues
Keywords: tf2,utils,sku
Classifier: Programming Language :: Python :: 3
Classifier: License :: OSI Approved :: MIT License
Classifier: Operating System :: OS Independent
Requires-Python: >=3.10
License-File: LICENSE
Requires-Dist: tf2-sku
Requires-Dist: tf2-data
Requires-Dist: bptf
Requires-Dist: requests
Requires-Dist: websocket-client
Dynamic: license-file
